hydtank/__init__.py
hydtank/basin_def.py
hydtank/basin_def_utils.py
hydtank/bsd_flow_node.py
hydtank/bsd_junction.py
hydtank/bsd_reach.py
hydtank/bsd_sink.py
hydtank/bsd_subbasin.py
hydtank/dataset.py
hydtank/hydtank.py
hydtank/parameters.py
hydtank/statistics.py
hydtank-1.1.1.dist-info/LICENSE
hydtank-1.1.1.dist-info/METADATA
hydtank-1.1.1.dist-info/WHEEL
hydtank-1.1.1.dist-info/RECORD
