Metadata-Version: 2.1
Name: hydtank
Version: 1.1.1
Summary: Python implementation of Tank Hydrological model by Sugawara and Funiyuki (1956).
Home-page: https://github.com/duynguyen02/HydTANK
License: MIT
Author: Duy Nguyen
Author-email: duynguyen02.dev@gmail.com
Requires-Python: >=3.10,<4.0
Classifier: License :: OSI Approved :: MIT License
Classifier: Programming Language :: Python :: 3
Classifier: Programming Language :: Python :: 3.10
Classifier: Programming Language :: Python :: 3.11
Classifier: Programming Language :: Python :: 3.12
Classifier: Programming Language :: Python :: 3.13
Requires-Dist: hydutils (>=1.0.0,<2.0.0)
Requires-Dist: matplotlib (>=3.9.2,<4.0.0)
Requires-Dist: networkx (>=3.4.2,<4.0.0)
Requires-Dist: pandas (>=2.2.3,<3.0.0)
Requires-Dist: spicy (>=0.16.0,<0.17.0)
Project-URL: Repository, https://github.com/duynguyen02/HydTANK
